hcscom/__init__.py
hcscom/hcscom.py
hcscom/lockfile.py
hcscom-0.5.8.dist-info/LICENSE
hcscom-0.5.8.dist-info/METADATA
hcscom-0.5.8.dist-info/WHEEL
hcscom-0.5.8.dist-info/top_level.txt
hcscom-0.5.8.dist-info/RECORD
