Metadata-Version: 2.1
Name: hcscom
Version: 0.5.8
Summary: An interface class to manson hcs lab power supplies
Home-page: https://gitlab.com/menschel/hcscom
Author: Patrick Menschel
Author-email: menschel.p@posteo.de
Keywords: remote psu power-supply
Classifier: Development Status :: 4 - Beta
Classifier: Programming Language :: Python :: 3
Classifier: License :: OSI Approved :: GNU General Public License v3 or later (GPLv3+)
Classifier: Operating System :: POSIX :: Linux
Classifier: Intended Audience :: Science/Research
Classifier: Intended Audience :: Developers
Classifier: Topic :: Scientific/Engineering
Classifier: Topic :: Software Development :: Embedded Systems
Classifier: Topic :: Utilities
Requires-Python: >=3.7
License-File: LICENSE
Requires-Dist: pyserial
Requires-Dist: psutil
